README.rst
setup.py
src/wellcome_storage_service/__init__.py
src/wellcome_storage_service/_utils.py
src/wellcome_storage_service/downloader.py
src/wellcome_storage_service/exceptions.py
src/wellcome_storage_service/secrets.py
src/wellcome_storage_service/version.py
src/wellcome_storage_service.egg-info/PKG-INFO
src/wellcome_storage_service.egg-info/SOURCES.txt
src/wellcome_storage_service.egg-info/dependency_links.txt
src/wellcome_storage_service.egg-info/requires.txt
src/wellcome_storage_service.egg-info/top_level.txt