Metadata-Version: 2.1
Name: wellcome-storage-service
Version: 2.3.4
Summary: A client for the Wellcome Storage Service
Home-page: https://github.com/wellcomecollection/storage-service
Author: Wellcome Trust (Digital Platform Team)
Author-email: wellcomedigitalplatform@wellcome.org
License: UNKNOWN
Platform: UNKNOWN
Classifier: Development Status :: 5 - Production/Stable
Classifier: Programming Language :: Python :: 2.7
Classifier: Programming Language :: Python :: 3.6
Classifier: Programming Language :: Python :: 3.7
Classifier: Topic :: Software Development
Classifier: Topic :: Utilities
Provides-Extra: s3
